<?xml version="1.0" encoding="utf-8"?>
<items>
<item><timestamp>2017-11-20 17:56:31.822116</timestamp><link>http://www.kreml.ru/visit-to-kremlin/what-to-see/sobornaya-ploschad/</link><title><value>Музеи Московского Кремля:  - Архитектурный ансамбль Московского Кремля</value></title></item>
<item><timestamp>2017-11-20 17:56:31.845797</timestamp><link>http://www.kreml.ru/museums-moscow-kremlin/</link><title><value>Музеи Московского Кремля: ГЛАВНАЯ</value></title></item>
<item><timestamp>2017-11-20 17:56:32.408665</timestamp><link>http://www.kreml.ru/learning/excursions/</link><title><value>Музеи Московского Кремля: ОБРАЗОВАНИЕ</value></title></item>
<item><timestamp>2017-11-20 17:56:32.545715</timestamp><link>http://www.kreml.ru/learning/kids/klub-lyubiteley-drevnostey/</link><title><value>Музеи Московского Кремля:  - Клуб Любителей Древностей (5-11 класс)</value></title></item>
<item><timestamp>2017-11-20 17:56:32.604382</timestamp><link>http://www.kreml.ru/learning/lectures/cikl-26-2017/</link><title><value>Музеи Московского Кремля:  - Цикл № 26. Мир человека Средневековья: культура России XVI–XVII веков</value></title></item>
<item><timestamp>2017-11-20 17:56:32.660260</timestamp><link>http://www.kreml.ru/visit-to-kremlin/ticket-prices/stoimost-vkhodnykh-biletov/</link><title><value>Музеи Московского Кремля:  - Входные билеты. Условия посещения</value></title></item>
<item><timestamp>2017-11-20 17:56:32.850921</timestamp><link>http://www.kreml.ru/visit-to-kremlin/what-to-see/</link><title><value>Музеи Московского Кремля: ПОСЕТИТЕЛЯМ</value></title></item>
<item><timestamp>2017-11-20 17:56:32.863377</timestamp><link>http://www.kreml.ru/learning/educational-programs/iskusstvo-emali-november/</link><title><value>Музеи Московского Кремля:  - Искусство эмали</value></title></item>
<item><timestamp>2017-11-20 17:56:32.871961</timestamp><link>http://www.kreml.ru/visit-to-kremlin/what-to-see/oruzheynaya-palata-zaly/</link><title><value>Музеи Московского Кремля:  - Оружейная палата</value></title></item>
<item><timestamp>2017-11-20 17:56:32.967191</timestamp><link>http://www.kreml.ru/learning/educational-programs/modniki-i-modnitsy-proshedshikh-vekov-xviii-xix-v/</link><title><value>Музеи Московского Кремля:  - Модники и модницы прошедших веков: XVIII–XIX в.</value></title></item>
<item><timestamp>2017-11-20 17:56:33.258674</timestamp><link>http://www.kreml.ru/learning/lectures/lektsionnye-programmy2/</link><title><value>Музеи Московского Кремля:  - Лекционные программы</value></title></item>
<item><timestamp>2017-11-20 17:56:33.584709</timestamp><link>http://www.kreml.ru/learning/kids/</link><title><value>Музеи Московского Кремля: ОБРАЗОВАНИЕ</value></title></item>
<item><timestamp>2017-11-20 17:56:33.614886</timestamp><link>http://www.kreml.ru/learning/excursions/drevniy-kreml-i-svyatye-obiteli/</link><title><value>Музеи Московского Кремля:  - Древний Кремль и святые обители</value></title></item>
<item><timestamp>2017-11-20 17:56:33.865010</timestamp><link>http://www.kreml.ru/calendar/</link><title><value>Музеи Московского Кремля: КАЛЕНДАРЬ СОБЫТИЙ</value></title></item>
<item><timestamp>2017-11-20 17:56:34.183718</timestamp><link>http://www.kreml.ru/quality/</link><title></title></item>
<item><timestamp>2017-11-20 17:56:34.205462</timestamp><link>http://www.kreml.ru/helper/article/redaktsiya-sayta-na-kitayskom-yazyke/</link><title></title></item>
<item><timestamp>2017-11-20 17:56:34.448161</timestamp><link>http://www.kreml.ru/shop/</link><title><value>Музеи Московского Кремля: МУЗЕЙНЫЙ МАГАЗИН</value></title></item>
<item><timestamp>2017-11-20 17:56:34.457295</timestamp><link>http://www.kreml.ru/press-room/</link><title><value>Музеи Московского Кремля: ПРЕСС-ЦЕНТР</value></title></item>
<item><timestamp>2017-11-20 17:56:34.483755</timestamp><link>http://www.kreml.ru/friends/view/</link><title><value>Музеи Московского Кремля: ДРУЗЬЯ МУЗЕЕВ</value></title></item>
<item><timestamp>2017-11-20 17:56:35.170298</timestamp><link>http://www.kreml.ru/visit-to-kremlin/what-to-see/artilleriyskie-orudiya/</link><title><value>Музеи Московского Кремля:  - Артиллерийские орудия</value></title></item>
<item><timestamp>2017-11-20 17:56:35.289693</timestamp><link>http://www.kreml.ru/visit-to-kremlin/what-to-see/ekspozitciya-klady-drevnosti/</link><title><value>Музеи Московского Кремля:  - Экспозиция «Клады и древности Московского Кремля»</value></title></item>
<item><timestamp>2017-11-20 17:56:35.328086</timestamp><link>http://www.kreml.ru/visit-to-kremlin/what-to-see/vistavka-derevyannoy-sculptury/</link><title><value>Музеи Московского Кремля:  - Выставка деревянной скульптуры</value></title></item>
<item><timestamp>2017-11-20 17:56:35.367979</timestamp><link>http://www.kreml.ru/visit-to-kremlin/what-to-see/tsar-kolokol/</link><title><value>Музеи Московского Кремля:  - Царь-колокол</value></title></item>
<item><timestamp>2017-11-20 17:56:35.481787</timestamp><link>http://www.kreml.ru/visit-to-kremlin/what-to-see/chto-posmotret-v-kremle-tsar-pushka/</link><title><value>Музеи Московского Кремля:  - Царь-пушка</value></title></item>
<item><timestamp>2017-11-20 17:56:35.528833</timestamp><link>http://www.kreml.ru/visit-to-kremlin/what-to-see/muzey-istorii-architectury-kremlya/</link><title><value>Музеи Московского Кремля:  - Музей истории архитектуры Московского Кремля в колокольне «Иван Великий»</value></title></item>
<item><timestamp>2017-11-20 17:56:35.549576</timestamp><link>http://www.kreml.ru/media-data/</link><title><value>Музеи Московского Кремля: МЕДИА</value></title></item>
<item><timestamp>2017-11-20 17:56:35.615697</timestamp><link>http://www.kreml.ru/visit-to-kremlin/what-to-see/patriarshie-palaty-s-tserkovyu-dvenadtsati-apostolov/</link><title><value>Музеи Московского Кремля:  - Патриаршие палаты с церковью Двенадцати апостолов</value></title></item>
<item><timestamp>2017-11-20 17:56:35.999966</timestamp><link>http://www.kreml.ru/learning/</link><title><value>Музеи Московского Кремля: ОБРАЗОВАНИЕ</value></title></item>
<item><timestamp>2017-11-20 17:56:36.258498</timestamp><link>http://www.kreml.ru/helper/subscribe.form/</link><title></title></item>
<item><timestamp>2017-11-20 17:56:36.366057</timestamp><link>http://www.kreml.ru/about-museums/contacts/</link><title><value>Музеи Московского Кремля: О МУЗЕЯХ</value></title></item>
<item><timestamp>2017-11-20 17:56:36.651188</timestamp><link>http://tickets.kreml.ru/ru/</link><title><value>Музеи Московского Кремля - Билеты</value></title></item>
<item><timestamp>2017-11-20 17:56:36.739073</timestamp><link>http://www.kreml.ru/exhibitions/</link><title><value>Музеи Московского Кремля: ВЫСТАВКИ</value></title></item>
<item><timestamp>2017-11-20 17:56:36.761616</timestamp><link>http://www.kreml.ru</link><title><value>Музеи Московского Кремля: ГЛАВНАЯ</value></title></item>
<item><timestamp>2017-11-20 17:56:36.833344</timestamp><link>http://www.kreml.ru/zh-CN/museums-moscow-kremlin/</link><title><value>莫斯科克里姆林宫博物馆: 主页</value></title></item>
<item><timestamp>2017-11-20 17:56:37.012900</timestamp><link>http://www.kreml.ru/visit-to-kremlin/</link><title><value>Музеи Московского Кремля: ПОСЕТИТЕЛЯМ</value></title></item>
<item><timestamp>2017-11-20 17:56:37.076740</timestamp><link>http://www.kreml.ru/en-Us/museums-moscow-kremlin/</link><title><value>Moscow Kremlin Museums: HOME</value></title></item>
<item><timestamp>2017-11-20 17:56:37.517206</timestamp><link>http://www.kreml.ru/about-museums/</link><title><value>Музеи Московского Кремля: О МУЗЕЯХ</value></title></item>
<item><timestamp>2017-11-20 17:56:38.129780</timestamp><link>http://www.kreml.ru/research/</link><title><value>Музеи Московского Кремля: НАУКА</value></title></item>
</items>